skill_creator_mcp/__init__.py
skill_creator_mcp/__main__.py
skill_creator_mcp/config.py
skill_creator_mcp/constants.py
skill_creator_mcp/http.py
skill_creator_mcp/logging_config.py
skill_creator_mcp/server.py
skill_creator_mcp/models/__init__.py
skill_creator_mcp/models/skill_config.py
skill_creator_mcp/prompts/__init__.py
skill_creator_mcp/prompts/create_skill.py
skill_creator_mcp/prompts/refactor_skill.py
skill_creator_mcp/prompts/validate_skill.py
skill_creator_mcp/resources/__init__.py
skill_creator_mcp/resources/best_practices.py
skill_creator_mcp/resources/templates.py
skill_creator_mcp/resources/validation_rules.py
skill_creator_mcp/templates/README.md
skill_creator_mcp/tools/package_tools.py
skill_creator_mcp/tools/phase0_tools.py
skill_creator_mcp/tools/requirement_question_tools.py
skill_creator_mcp/tools/requirement_session_tools.py
skill_creator_mcp/tools/requirement_validation_tools.py
skill_creator_mcp/tools/skill_tools.py
skill_creator_mcp/utils/__init__.py
skill_creator_mcp/utils/analyzers.py
skill_creator_mcp/utils/cache.py
skill_creator_mcp/utils/capability_detection.py
skill_creator_mcp/utils/file_ops.py
skill_creator_mcp/utils/packagers.py
skill_creator_mcp/utils/path_helpers.py
skill_creator_mcp/utils/refactorors.py
skill_creator_mcp/utils/skill_generators.py
skill_creator_mcp/utils/testing.py
skill_creator_mcp/utils/validators.py
skill_creator_mcp/utils/requirement_collection/__init__.py
skill_creator_mcp/utils/requirement_collection/llm_services.py
skill_creator_mcp/utils/requirement_collection/questions.py
skill_creator_mcp/utils/requirement_collection/session_manager.py
skill_creator_mcp/utils/requirement_collection/validation.py
skill_creator_mcp-0.3.6.dist-info/METADATA
skill_creator_mcp-0.3.6.dist-info/WHEEL
skill_creator_mcp-0.3.6.dist-info/entry_points.txt
skill_creator_mcp-0.3.6.dist-info/licenses/LICENSE
skill_creator_mcp-0.3.6.dist-info/RECORD
