Metadata-Version: 2.4
Name: skill-creator-mcp
Version: 0.3.6
Summary: Agent-Skills 开发与质量保证 MCP Server
Project-URL: Homepage, https://github.com/skill-creator/skill-creator-mcp
Project-URL: Documentation, https://github.com/skill-creator/skill-creator-mcp#readme
Project-URL: Repository, https://github.com/skill-creator/skill-creator-mcp
Project-URL: Issues, https://github.com/skill-creator/skill-creator-mcp/issues
Author: Skill Creator Team
License: MIT
License-File: LICENSE
Keywords: agent-skills,ai,claude,mcp
Classifier: Development Status :: 3 - Alpha
Classifier: Intended Audience :: Developers
Classifier: License :: OSI Approved :: MIT License
Classifier: Programming Language :: Python :: 3
Classifier: Programming Language :: Python :: 3.10
Classifier: Programming Language :: Python :: 3.11
Classifier: Programming Language :: Python :: 3.12
Classifier: Topic :: Software Development :: Libraries :: Python Modules
Requires-Python: >=3.10
Requires-Dist: aiofiles>=23.0.0
Requires-Dist: aiohttp>=3.9.0
Requires-Dist: fastmcp>=3.0.0b1
Requires-Dist: jinja2>=3.1.0
Requires-Dist: pydantic>=2.0.0
Requires-Dist: pyyaml>=6.0
Requires-Dist: rich>=13.0.0
Provides-Extra: dev
Requires-Dist: bandit>=1.7.0; extra == 'dev'
Requires-Dist: mypy>=1.0.0; extra == 'dev'
Requires-Dist: pre-commit>=3.0.0; extra == 'dev'
Requires-Dist: pytest-asyncio>=0.21.0; extra == 'dev'
Requires-Dist: pytest-cov>=4.0.0; extra == 'dev'
Requires-Dist: pytest>=7.0.0; extra == 'dev'
Requires-Dist: ruff>=0.1.0; extra == 'dev'
Requires-Dist: sphinx-autodoc-typehints>=2.0.0; extra == 'dev'
Requires-Dist: sphinx-rtd-theme>=2.0.0; extra == 'dev'
Requires-Dist: sphinx>=7.0.0; extra == 'dev'
Provides-Extra: sse
Requires-Dist: starlette>=0.27.0; extra == 'sse'
Requires-Dist: uvicorn[standard]>=0.24.0; extra == 'sse'
